setup.cfg
setup.py
manyquery/__init__.py
manyquery/cli.py
manyquery/connection.py
manyquery.egg-info/PKG-INFO
manyquery.egg-info/SOURCES.txt
manyquery.egg-info/dependency_links.txt
manyquery.egg-info/entry_points.txt
manyquery.egg-info/requires.txt
manyquery.egg-info/top_level.txt