Metadata-Version: 1.1
Name: manyquery
Version: 0.0.1
Summary: UNKNOWN
Home-page: UNKNOWN
Author: Billy Jarnagin
Author-email: jarnabi@gmail.com
License: The MIT License (MIT)
